py2ppt/__init__.py
py2ppt/accessibility.py
py2ppt/analysis.py
py2ppt/builder.py
py2ppt/diff.py
py2ppt/errors.py
py2ppt/export.py
py2ppt/formatting.py
py2ppt/layout.py
py2ppt/markdown.py
py2ppt/patterns.py
py2ppt/placeholders.py
py2ppt/presentation.py
py2ppt/shapes.py
py2ppt/template.py
py2ppt/theme.py
py2ppt/validation.py
py2ppt-0.2.0.dist-info/licenses/LICENSE
py2ppt-0.2.0.dist-info/METADATA
py2ppt-0.2.0.dist-info/WHEEL
py2ppt-0.2.0.dist-info/top_level.txt
py2ppt-0.2.0.dist-info/RECORD
