Metadata-Version: 2.4
Name: py2ppt
Version: 0.2.0
Summary: AI-Friendly PowerPoint Wrapper
Author: py2ppt contributors
License: MIT
Project-URL: Homepage, https://github.com/lhassa8/py2ppt
Project-URL: Documentation, https://github.com/lhassa8/py2ppt#readme
Project-URL: Repository, https://github.com/lhassa8/py2ppt
Project-URL: Issues, https://github.com/lhassa8/py2ppt/issues
Project-URL: Changelog, https://github.com/lhassa8/py2ppt/blob/main/CHANGELOG.md
Keywords: powerpoint,pptx,presentation,ai,llm,openxml
Classifier: Development Status :: 3 - Alpha
Classifier: Intended Audience :: Developers
Classifier: License :: OSI Approved :: MIT License
Classifier: Programming Language :: Python :: 3
Classifier: Programming Language :: Python :: 3.10
Classifier: Programming Language :: Python :: 3.11
Classifier: Programming Language :: Python :: 3.12
Classifier: Topic :: Office/Business
Classifier: Topic :: Software Development :: Libraries :: Python Modules
Classifier: Typing :: Typed
Requires-Python: >=3.10
License-File: LICENSE
Requires-Dist: python-pptx>=0.6.21
Provides-Extra: dev
Requires-Dist: pytest>=7.0; extra == "dev"
Requires-Dist: pytest-cov>=4.0; extra == "dev"
Requires-Dist: ruff>=0.1.0; extra == "dev"
Requires-Dist: mypy>=1.0; extra == "dev"
Requires-Dist: pre-commit>=3.0; extra == "dev"
Provides-Extra: images
Requires-Dist: Pillow>=9.0; extra == "images"
Provides-Extra: all
Requires-Dist: py2ppt[dev,images]; extra == "all"
Dynamic: license-file
